[
  {
    "symbol":"AAMI",
    "cond1":true,
    "cond2":true,
    "cond3":true,
    "cond4":true,
    "cond5":true,
    "cond6":true,
    "cond7":true,
    "cond8":true,
    "bars":330,
    "tv_median20":17478185.7559204102,
    "distance_to_52w_high":0.017240005,
    "met_count":7,
    "close":66.4100036621,
    "volume":289500.0,
    "date":"2026-04-16",
    "rs_score":91.15,
    "rs_benchmark":"SPY",
    "recommended_rs_pass":true,
    "recommended_distance_to_high_pass":true,
    "met_count_fin":7,
    "rs_score_fin":91.15,
    "provider_symbol":"AAMI",
    "fin_met_count":7,
    "fetch_status":"complete",
    "unavailable_reason":null,
    "has_error":false,
    "rs_percentile":65.0,
    "fin_percentile":100.0,
    "total_percentile":165.0,
    "total_met_count":14
  },
  {
    "symbol":"AAOI",
    "cond1":true,
    "cond2":true,
    "cond3":true,
    "cond4":true,
    "cond5":true,
    "cond6":true,
    "cond7":true,
    "cond8":true,
    "bars":330,
    "tv_median20":1408773591.4619445801,
    "distance_to_52w_high":0.0005081739,
    "met_count":7,
    "close":157.3200073242,
    "volume":10634600.0,
    "date":"2026-04-16",
    "rs_score":99.12,
    "rs_benchmark":"SPY",
    "recommended_rs_pass":true,
    "recommended_distance_to_high_pass":true,
    "met_count_fin":7,
    "rs_score_fin":99.12,
    "provider_symbol":"AAOI",
    "fin_met_count":6,
    "fetch_status":"complete",
    "unavailable_reason":null,
    "has_error":false,
    "rs_percentile":95.0,
    "fin_percentile":77.5,
    "total_percentile":172.5,
    "total_met_count":13
  },
  {
    "symbol":"AAUC",
    "cond1":true,
    "cond2":true,
    "cond3":true,
    "cond4":true,
    "cond5":true,
    "cond6":true,
    "cond7":true,
    "cond8":true,
    "bars":330,
    "tv_median20":10241979.4983863849,
    "distance_to_52w_high":0.0052993134,
    "met_count":7,
    "close":31.9099998474,
    "volume":284500.0,
    "date":"2026-04-16",
    "rs_score":94.69,
    "rs_benchmark":"SPY",
    "recommended_rs_pass":true,
    "recommended_distance_to_high_pass":true,
    "met_count_fin":7,
    "rs_score_fin":94.69,
    "provider_symbol":"AAUC",
    "fin_met_count":6,
    "fetch_status":"complete",
    "unavailable_reason":null,
    "has_error":false,
    "rs_percentile":80.0,
    "fin_percentile":77.5,
    "total_percentile":157.5,
    "total_met_count":13
  },
  {
    "symbol":"ACTG",
    "cond1":true,
    "cond2":true,
    "cond3":true,
    "cond4":true,
    "cond5":true,
    "cond6":true,
    "cond7":true,
    "cond8":true,
    "bars":330,
    "tv_median20":1337765.0080919266,
    "distance_to_52w_high":0.0440613081,
    "met_count":7,
    "close":4.9899997711,
    "volume":246100.0,
    "date":"2026-04-16",
    "rs_score":88.5,
    "rs_benchmark":"SPY",
    "recommended_rs_pass":true,
    "recommended_distance_to_high_pass":true,
    "met_count_fin":7,
    "rs_score_fin":88.5,
    "provider_symbol":"ACTG",
    "fin_met_count":6,
    "fetch_status":"complete",
    "unavailable_reason":null,
    "has_error":false,
    "rs_percentile":60.0,
    "fin_percentile":77.5,
    "total_percentile":137.5,
    "total_met_count":13
  },
  {
    "symbol":"AAXJ",
    "cond1":true,
    "cond2":true,
    "cond3":true,
    "cond4":true,
    "cond5":true,
    "cond6":true,
    "cond7":true,
    "cond8":true,
    "bars":330,
    "tv_median20":119909550.0,
    "distance_to_52w_high":0.0158553464,
    "met_count":7,
    "close":106.1399993896,
    "volume":1495900.0,
    "date":"2026-04-16",
    "rs_score":79.65,
    "rs_benchmark":"SPY",
    "recommended_rs_pass":true,
    "recommended_distance_to_high_pass":true,
    "met_count_fin":7,
    "rs_score_fin":79.65,
    "provider_symbol":"AAXJ",
    "fin_met_count":6,
    "fetch_status":"soft_unavailable",
    "unavailable_reason":"ineligible:etf",
    "has_error":true,
    "rs_percentile":45.0,
    "fin_percentile":77.5,
    "total_percentile":122.5,
    "total_met_count":13
  },
  {
    "symbol":"AAVM",
    "cond1":true,
    "cond2":true,
    "cond3":true,
    "cond4":true,
    "cond5":true,
    "cond6":true,
    "cond7":true,
    "cond8":true,
    "bars":330,
    "tv_median20":54580.0498008728,
    "distance_to_52w_high":0.0162401273,
    "met_count":7,
    "close":33.4379997253,
    "volume":200.0,
    "date":"2026-04-16",
    "rs_score":77.88,
    "rs_benchmark":"SPY",
    "recommended_rs_pass":true,
    "recommended_distance_to_high_pass":true,
    "met_count_fin":7,
    "rs_score_fin":77.88,
    "provider_symbol":"AAVM",
    "fin_met_count":6,
    "fetch_status":"soft_unavailable",
    "unavailable_reason":"ineligible:etf",
    "has_error":true,
    "rs_percentile":40.0,
    "fin_percentile":77.5,
    "total_percentile":117.5,
    "total_met_count":13
  },
  {
    "symbol":"ACES",
    "cond1":true,
    "cond2":true,
    "cond3":true,
    "cond4":true,
    "cond5":true,
    "cond6":true,
    "cond7":true,
    "cond8":true,
    "bars":330,
    "tv_median20":1562914.0594482422,
    "distance_to_52w_high":0.0765238228,
    "met_count":7,
    "close":34.6949996948,
    "volume":102700.0,
    "date":"2026-04-16",
    "rs_score":73.45,
    "rs_benchmark":"SPY",
    "recommended_rs_pass":true,
    "recommended_distance_to_high_pass":true,
    "met_count_fin":7,
    "rs_score_fin":73.45,
    "provider_symbol":"ACES",
    "fin_met_count":6,
    "fetch_status":"soft_unavailable",
    "unavailable_reason":"ineligible:etf",
    "has_error":true,
    "rs_percentile":30.0,
    "fin_percentile":77.5,
    "total_percentile":107.5,
    "total_met_count":13
  },
  {
    "symbol":"ABFL",
    "cond1":true,
    "cond2":true,
    "cond3":true,
    "cond4":true,
    "cond5":true,
    "cond6":true,
    "cond7":true,
    "cond8":false,
    "bars":330,
    "tv_median20":2005125.9819030759,
    "distance_to_52w_high":0.0026551456,
    "met_count":7,
    "close":75.8779983521,
    "volume":33600.0,
    "date":"2026-04-16",
    "rs_score":66.37,
    "rs_benchmark":"SPY",
    "recommended_rs_pass":false,
    "recommended_distance_to_high_pass":true,
    "met_count_fin":7,
    "rs_score_fin":66.37,
    "provider_symbol":"ABFL",
    "fin_met_count":6,
    "fetch_status":"soft_unavailable",
    "unavailable_reason":"ineligible:etf",
    "has_error":true,
    "rs_percentile":15.0,
    "fin_percentile":77.5,
    "total_percentile":92.5,
    "total_met_count":13
  },
  {
    "symbol":"ABCS",
    "cond1":true,
    "cond2":true,
    "cond3":true,
    "cond4":true,
    "cond5":true,
    "cond6":true,
    "cond7":true,
    "cond8":false,
    "bars":330,
    "tv_median20":67761.0998153687,
    "distance_to_52w_high":0.0154063733,
    "met_count":7,
    "close":31.3789997101,
    "volume":1100.0,
    "date":"2026-04-16",
    "rs_score":58.41,
    "rs_benchmark":"SPY",
    "recommended_rs_pass":false,
    "recommended_distance_to_high_pass":true,
    "met_count_fin":7,
    "rs_score_fin":58.41,
    "provider_symbol":"ABCS",
    "fin_met_count":6,
    "fetch_status":"soft_unavailable",
    "unavailable_reason":"ineligible:etf",
    "has_error":true,
    "rs_percentile":10.0,
    "fin_percentile":77.5,
    "total_percentile":87.5,
    "total_met_count":13
  },
  {
    "symbol":"ACLS",
    "cond1":true,
    "cond2":true,
    "cond3":true,
    "cond4":true,
    "cond5":true,
    "cond6":true,
    "cond7":true,
    "cond8":true,
    "bars":330,
    "tv_median20":64140269.5747375488,
    "distance_to_52w_high":0.0184312403,
    "met_count":7,
    "close":118.7600021362,
    "volume":693000.0,
    "date":"2026-04-16",
    "rs_score":92.04,
    "rs_benchmark":"SPY",
    "recommended_rs_pass":true,
    "recommended_distance_to_high_pass":true,
    "met_count_fin":7,
    "rs_score_fin":92.04,
    "provider_symbol":"ACLS",
    "fin_met_count":5,
    "fetch_status":"complete",
    "unavailable_reason":null,
    "has_error":false,
    "rs_percentile":70.0,
    "fin_percentile":55.0,
    "total_percentile":125.0,
    "total_met_count":12
  },
  {
    "symbol":"AA",
    "cond1":true,
    "cond2":true,
    "cond3":true,
    "cond4":true,
    "cond5":true,
    "cond6":true,
    "cond7":true,
    "cond8":true,
    "bars":330,
    "tv_median20":353562364.5595550537,
    "distance_to_52w_high":0.0698810238,
    "met_count":7,
    "close":70.4100036621,
    "volume":6258800.0,
    "date":"2026-04-16",
    "rs_score":95.58,
    "rs_benchmark":"SPY",
    "recommended_rs_pass":true,
    "recommended_distance_to_high_pass":true,
    "met_count_fin":7,
    "rs_score_fin":95.58,
    "provider_symbol":"AA",
    "fin_met_count":4,
    "fetch_status":"complete",
    "unavailable_reason":null,
    "has_error":false,
    "rs_percentile":85.0,
    "fin_percentile":45.0,
    "total_percentile":130.0,
    "total_met_count":11
  },
  {
    "symbol":"ABEV",
    "cond1":true,
    "cond2":true,
    "cond3":true,
    "cond4":true,
    "cond5":true,
    "cond6":true,
    "cond7":true,
    "cond8":true,
    "bars":330,
    "tv_median20":74285285.0284934044,
    "distance_to_52w_high":0.0586419928,
    "met_count":7,
    "close":3.0499999523,
    "volume":24920500.0,
    "date":"2026-04-16",
    "rs_score":83.19,
    "rs_benchmark":"SPY",
    "recommended_rs_pass":true,
    "recommended_distance_to_high_pass":true,
    "met_count_fin":7,
    "rs_score_fin":83.19,
    "provider_symbol":"ABEV",
    "fin_met_count":4,
    "fetch_status":"complete",
    "unavailable_reason":null,
    "has_error":false,
    "rs_percentile":50.0,
    "fin_percentile":45.0,
    "total_percentile":95.0,
    "total_met_count":11
  },
  {
    "symbol":"ABCB",
    "cond1":true,
    "cond2":true,
    "cond3":true,
    "cond4":true,
    "cond5":true,
    "cond6":true,
    "cond7":true,
    "cond8":true,
    "bars":330,
    "tv_median20":40117920.5230712891,
    "distance_to_52w_high":0.0608093419,
    "met_count":7,
    "close":82.6299972534,
    "volume":460900.0,
    "date":"2026-04-16",
    "rs_score":76.99,
    "rs_benchmark":"SPY",
    "recommended_rs_pass":true,
    "recommended_distance_to_high_pass":true,
    "met_count_fin":7,
    "rs_score_fin":76.99,
    "provider_symbol":"ABCB",
    "fin_met_count":4,
    "fetch_status":"complete",
    "unavailable_reason":null,
    "has_error":false,
    "rs_percentile":35.0,
    "fin_percentile":45.0,
    "total_percentile":80.0,
    "total_met_count":11
  },
  {
    "symbol":"ABX",
    "cond1":true,
    "cond2":true,
    "cond3":true,
    "cond4":true,
    "cond5":true,
    "cond6":true,
    "cond7":true,
    "cond8":true,
    "bars":310,
    "tv_median20":6194568.5529708862,
    "distance_to_52w_high":0.103939277,
    "met_count":7,
    "close":9.4399995804,
    "volume":1078200.0,
    "date":"2026-03-18",
    "rs_score":84.96,
    "rs_benchmark":"SPY",
    "recommended_rs_pass":true,
    "recommended_distance_to_high_pass":true,
    "met_count_fin":7,
    "rs_score_fin":84.96,
    "provider_symbol":"ABX",
    "fin_met_count":3,
    "fetch_status":"complete",
    "unavailable_reason":null,
    "has_error":false,
    "rs_percentile":55.0,
    "fin_percentile":35.0,
    "total_percentile":90.0,
    "total_met_count":10
  },
  {
    "symbol":"ACRE",
    "cond1":true,
    "cond2":true,
    "cond3":true,
    "cond4":true,
    "cond5":true,
    "cond6":true,
    "cond7":true,
    "cond8":true,
    "bars":330,
    "tv_median20":1764439.5293712616,
    "distance_to_52w_high":0.1256366363,
    "met_count":7,
    "close":5.1500000954,
    "volume":344200.0,
    "date":"2026-04-16",
    "rs_score":71.68,
    "rs_benchmark":"SPY",
    "recommended_rs_pass":true,
    "recommended_distance_to_high_pass":true,
    "met_count_fin":7,
    "rs_score_fin":71.68,
    "provider_symbol":"ACRE",
    "fin_met_count":2,
    "fetch_status":"complete",
    "unavailable_reason":null,
    "has_error":false,
    "rs_percentile":25.0,
    "fin_percentile":25.0,
    "total_percentile":50.0,
    "total_met_count":9
  },
  {
    "symbol":"ACNB",
    "cond1":true,
    "cond2":true,
    "cond3":true,
    "cond4":true,
    "cond5":true,
    "cond6":true,
    "cond7":true,
    "cond8":false,
    "bars":330,
    "tv_median20":3128821.5179443359,
    "distance_to_52w_high":0.0634625758,
    "met_count":7,
    "close":50.4700012207,
    "volume":65600.0,
    "date":"2026-04-16",
    "rs_score":68.14,
    "rs_benchmark":"SPY",
    "recommended_rs_pass":false,
    "recommended_distance_to_high_pass":true,
    "met_count_fin":7,
    "rs_score_fin":68.14,
    "provider_symbol":"ACNB",
    "fin_met_count":2,
    "fetch_status":"complete",
    "unavailable_reason":null,
    "has_error":false,
    "rs_percentile":20.0,
    "fin_percentile":25.0,
    "total_percentile":45.0,
    "total_met_count":9
  },
  {
    "symbol":"AAON",
    "cond1":true,
    "cond2":true,
    "cond3":true,
    "cond4":true,
    "cond5":true,
    "cond6":true,
    "cond7":true,
    "cond8":false,
    "bars":330,
    "tv_median20":57244698.8143920898,
    "distance_to_52w_high":0.2116511321,
    "met_count":7,
    "close":91.4800033569,
    "volume":780300.0,
    "date":"2026-04-16",
    "rs_score":49.56,
    "rs_benchmark":"SPY",
    "recommended_rs_pass":false,
    "recommended_distance_to_high_pass":false,
    "met_count_fin":7,
    "rs_score_fin":49.56,
    "provider_symbol":"AAON",
    "fin_met_count":2,
    "fetch_status":"complete",
    "unavailable_reason":null,
    "has_error":false,
    "rs_percentile":5.0,
    "fin_percentile":25.0,
    "total_percentile":30.0,
    "total_met_count":9
  },
  {
    "symbol":"ABVX",
    "cond1":true,
    "cond2":true,
    "cond3":true,
    "cond4":true,
    "cond5":true,
    "cond6":true,
    "cond7":true,
    "cond8":true,
    "bars":330,
    "tv_median20":122622697.3209381253,
    "distance_to_52w_high":0.1771148309,
    "met_count":7,
    "close":122.4700012207,
    "volume":745300.0,
    "date":"2026-04-16",
    "rs_score":100.0,
    "rs_benchmark":"SPY",
    "recommended_rs_pass":true,
    "recommended_distance_to_high_pass":false,
    "met_count_fin":7,
    "rs_score_fin":100.0,
    "provider_symbol":"ABVX",
    "fin_met_count":1,
    "fetch_status":"complete",
    "unavailable_reason":null,
    "has_error":false,
    "rs_percentile":100.0,
    "fin_percentile":10.0,
    "total_percentile":110.0,
    "total_met_count":8
  },
  {
    "symbol":"ACRS",
    "cond1":true,
    "cond2":true,
    "cond3":true,
    "cond4":true,
    "cond5":true,
    "cond6":true,
    "cond7":true,
    "cond8":true,
    "bars":330,
    "tv_median20":5295919.9929237366,
    "distance_to_52w_high":0.1860940434,
    "met_count":7,
    "close":3.9800000191,
    "volume":1108200.0,
    "date":"2026-04-16",
    "rs_score":97.35,
    "rs_benchmark":"SPY",
    "recommended_rs_pass":true,
    "recommended_distance_to_high_pass":false,
    "met_count_fin":7,
    "rs_score_fin":97.35,
    "provider_symbol":"ACRS",
    "fin_met_count":1,
    "fetch_status":"complete",
    "unavailable_reason":null,
    "has_error":false,
    "rs_percentile":90.0,
    "fin_percentile":10.0,
    "total_percentile":100.0,
    "total_met_count":8
  },
  {
    "symbol":"ACLX",
    "cond1":true,
    "cond2":true,
    "cond3":true,
    "cond4":true,
    "cond5":true,
    "cond6":true,
    "cond7":true,
    "cond8":true,
    "bars":330,
    "tv_median20":116715337.3363494873,
    "distance_to_52w_high":0.0002605644,
    "met_count":7,
    "close":115.0999984741,
    "volume":434600.0,
    "date":"2026-04-16",
    "rs_score":92.92,
    "rs_benchmark":"SPY",
    "recommended_rs_pass":true,
    "recommended_distance_to_high_pass":true,
    "met_count_fin":7,
    "rs_score_fin":92.92,
    "provider_symbol":"ACLX",
    "fin_met_count":1,
    "fetch_status":"complete",
    "unavailable_reason":null,
    "has_error":false,
    "rs_percentile":75.0,
    "fin_percentile":10.0,
    "total_percentile":85.0,
    "total_met_count":8
  }
]