{"identity":{"schema_version":"1","namespace":"leader_lagging_features","market":"us","symbol":"ABG","as_of":"2026-04-24","feature_version":"leader_lagging_features_v1","source":{"path":"E:\\side project\\invest-prototype-main\\data\\us\\ABG.csv","mtime_ns":1777175625642504100,"size":42465},"extra_hash":"93779d5edaf31c8dbb8e2bf7"},"row":{"symbol":"ABG","market":"US","as_of_ts":"2026-04-24","sector":"Consumer Cyclical","industry":"Auto & Truck Dealerships","bars":330,"close":203.05999755859372,"ma50":204.98859924316406,"ma150":226.84599934895834,"ma200":230.60884994506836,"ma200_slope_20d":-0.01836389382923309,"close_gt_50":false,"close_gt_200":false,"weighted_rs_raw":-25.567001524591664,"weighted_rs_prev_raw":-12.489086121731848,"rs_rank_proxy_raw":11.051282051282051,"rs_proxy_sample_count":78,"rs_proxy_component_coverage":4,"rs_proxy_confidence":100.0,"mom_12_1":-0.19917475987949107,"rs_line":0.28442165569124145,"rs_line_slope":-0.07591251227374152,"rs_line_20d_slope":-0.07591251227374152,"rs_line_65d_high_flag":false,"rs_line_250d_high_flag":false,"rs_new_high_before_price_flag":false,"rs_line_distance_to_high":0.3307637634661037,"benchmark_relative_strength":0.8235648698523255,"benchmark_relative_strength_slope":-0.047707450603053814,"hidden_rs_raw":-7.142074795021272,"hidden_rs_weak_day_count":56,"hidden_rs_down_day_excess_return":0.0010446258472848902,"hidden_rs_drawdown_resilience":-0.13874350294626706,"hidden_rs_weak_window_excess_return":-0.18756851596895002,"hidden_rs_confidence":100.0,"distance_to_52w_high":0.23653044844672688,"distance_from_52w_low":0.0971471555525032,"distance_from_ma50":0.009408336325487876,"ret_20d":0.02271465342491208,"ret_60d":-0.16741154591510354,"ret_120d":-0.1475946750144409,"ret_252d":-0.07409602927772785,"adv20":214190.0,"adv50":229982.0,"traded_value":55110483.33740234,"traded_value_20d":43274568.90861511,"traded_value_50d":47019723.52093506,"atr20_pct":3.0619023215061305,"rvol":1.1800923550538738,"up_volume_ratio":0.7606083364626361,"distribution_day_count_20d":4,"illiq":2.7521053521283153e-10,"trend_integrity_score":20.0,"base_length":25.0,"base_tightness":85.62218825089522,"volatility_contraction":15.786275665763716,"range_compression":-6.04094824218655,"pivot_proximity":41.79303828101124,"breakout_volume_expansion":1.2670993043559458,"structure_quality_score":35.474194363881296,"recent_pivot_high":215.6100006103516,"box_high":215.6100006103516,"box_low":184.6100006103516,"box_valid":false,"breakout_confirmed":false,"structure_readiness_score":48.94214431977837,"breakout_confirmation_score":34.26854161525482,"dry_volume_ratio":1.604369951911854,"box_touch_count":3,"support_hold_count":24,"dry_volume_score":0.0,"failed_breakout_risk_score":100.0,"breakout_quality_score":37.44753560153811,"structure_confidence":95.0,"base_depth_pct":14.37781174910477,"loose_base_risk_score":18.239634354417298,"support_violation_count":1,"breakout_failure_count":2,"breakout_volume_quality_score":66.72847205084939,"structure_reject_reason_codes":"failed_breakout","event_gap_up_flag":false,"event_proxy_score":23.105217889906818,"market_cap":3918188800.0,"industry_key":"consumer_cyclical__auto_&_truck_dealerships","group_name":"Auto & Truck Dealerships"}}