[
  {
    "종목명":"ORCL",
    "매수일":"2025-06-20",
    "매수가":204.54,
    "비중(%)":10.0,
    "수익률":0.0,
    "차익실현":"166.34 (10일 ATR 상단) 또는 6일 후 강제매도",
    "손절매":179.74,
    "수익보호":"없음",
    "롱여부":true
  },
  {
    "종목명":"ELF",
    "매수일":"2025-06-20",
    "매수가":118.57,
    "비중(%)":10.0,
    "수익률":0.0,
    "차익실현":"83.15 (10일 ATR 상단) 또는 6일 후 강제매도",
    "손절매":102.5,
    "수익보호":"없음",
    "롱여부":true
  },
  {
    "종목명":"TMDX",
    "매수일":"2025-06-20",
    "매수가":120.28,
    "비중(%)":10.0,
    "수익률":0.0,
    "차익실현":"96.54 (10일 ATR 상단) 또는 6일 후 강제매도",
    "손절매":102.18,
    "수익보호":"없음",
    "롱여부":true
  },
  {
    "종목명":"NBIS",
    "매수일":"2025-06-20",
    "매수가":45.72,
    "비중(%)":7.39,
    "수익률":0.0,
    "차익실현":"36.1 (10일 ATR 상단) 또는 6일 후 강제매도",
    "손절매":33.34,
    "수익보호":"없음",
    "롱여부":true
  },
  {
    "종목명":"NXPI",
    "매수일":"2025-06-20",
    "매수가":204.57,
    "비중(%)":10.0,
    "수익률":0.0,
    "차익실현":"209.35 (10일 ATR 상단) 또는 6일 후 강제매도",
    "손절매":183.46,
    "수익보호":"없음",
    "롱여부":true
  },
  {
    "종목명":"META",
    "매수일":"2025-06-20",
    "매수가":662.38,
    "비중(%)":10.0,
    "수익률":0.0,
    "차익실현":"641.25 (10일 ATR 상단) 또는 6일 후 강제매도",
    "손절매":616.26,
    "수익보호":"없음",
    "롱여부":true
  },
  {
    "종목명":"OKLO",
    "매수일":"2025-06-20",
    "매수가":60.16,
    "비중(%)":5.65,
    "수익률":0.0,
    "차익실현":"43.06 (10일 ATR 상단) 또는 6일 후 강제매도",
    "손절매":38.86,
    "수익보호":"없음",
    "롱여부":true
  },
  {
    "종목명":"SOXX",
    "매수일":"2025-06-20",
    "매수가":214.33,
    "비중(%)":10.0,
    "수익률":0.0,
    "차익실현":"207.79 (10일 ATR 상단) 또는 6일 후 강제매도",
    "손절매":198.0,
    "수익보호":"없음",
    "롱여부":true
  },
  {
    "종목명":"ANSS",
    "매수일":"2025-06-20",
    "매수가":327.87,
    "비중(%)":10.0,
    "수익률":0.0,
    "차익실현":"334.6 (10일 ATR 상단) 또는 6일 후 강제매도",
    "손절매":312.11,
    "수익보호":"없음",
    "롱여부":true
  },
  {
    "종목명":"TT",
    "매수일":"2025-06-20",
    "매수가":407.26,
    "비중(%)":10.0,
    "수익률":0.0,
    "차익실현":"380.41 (10일 ATR 상단) 또는 6일 후 강제매도",
    "손절매":386.12,
    "수익보호":"없음",
    "롱여부":true
  }
]