[
  {
    "종목명":"BSLK",
    "매수일":"2025-08-20",
    "매수가":6.53,
    "비중(%)":1.6,
    "수익률":0.0,
    "차익실현":"6.79 (4% 수익) 또는 3일 후 청산",
    "손절매":-1.63,
    "수익보호":"없음",
    "롱여부":true
  },
  {
    "종목명":"CHSN",
    "매수일":"2025-08-20",
    "매수가":3.05,
    "비중(%)":2.07,
    "수익률":0.0,
    "차익실현":"3.17 (4% 수익) 또는 3일 후 청산",
    "손절매":0.1,
    "수익보호":"없음",
    "롱여부":true
  },
  {
    "종목명":"TNXP",
    "매수일":"2025-08-20",
    "매수가":37.27,
    "비중(%)":3.59,
    "수익률":0.0,
    "차익실현":"38.76 (4% 수익) 또는 3일 후 청산",
    "손절매":16.53,
    "수익보호":"없음",
    "롱여부":true
  },
  {
    "종목명":"ATNF",
    "매수일":"2025-08-20",
    "매수가":6.89,
    "비중(%)":2.11,
    "수익률":0.0,
    "차익실현":"7.17 (4% 수익) 또는 3일 후 청산",
    "손절매":0.36,
    "수익보호":"없음",
    "롱여부":true
  },
  {
    "종목명":"CLDI",
    "매수일":"2025-08-20",
    "매수가":3.81,
    "비중(%)":3.3,
    "수익률":0.0,
    "차익실현":"3.97 (4% 수익) 또는 3일 후 청산",
    "손절매":1.5,
    "수익보호":"없음",
    "롱여부":true
  },
  {
    "종목명":"AREC",
    "매수일":"2025-08-20",
    "매수가":1.18,
    "비중(%)":4.08,
    "수익률":0.0,
    "차익실현":"1.23 (4% 수익) 또는 3일 후 청산",
    "손절매":0.6,
    "수익보호":"없음",
    "롱여부":true
  },
  {
    "종목명":"SY",
    "매수일":"2025-08-20",
    "매수가":3.36,
    "비중(%)":4.93,
    "수익률":0.0,
    "차익실현":"3.5 (4% 수익) 또는 3일 후 청산",
    "손절매":2.0,
    "수익보호":"없음",
    "롱여부":true
  },
  {
    "종목명":"MPU",
    "매수일":"2025-08-20",
    "매수가":2.35,
    "비중(%)":3.5,
    "수익률":0.0,
    "차익실현":"2.45 (4% 수익) 또는 3일 후 청산",
    "손절매":1.01,
    "수익보호":"없음",
    "롱여부":true
  },
  {
    "종목명":"PPCB",
    "매수일":"2025-08-20",
    "매수가":5.44,
    "비중(%)":1.14,
    "수익률":0.0,
    "차익실현":"5.66 (4% 수익) 또는 3일 후 청산",
    "손절매":-4.12,
    "수익보호":"없음",
    "롱여부":true
  },
  {
    "종목명":"ELWS",
    "매수일":"2025-08-20",
    "매수가":2.74,
    "비중(%)":1.46,
    "수익률":0.0,
    "차익실현":"2.85 (4% 수익) 또는 3일 후 청산",
    "손절매":-1.03,
    "수익보호":"없음",
    "롱여부":true
  }
]