[
  {
    "종목명":"ORCL",
    "entry_price":204.54,
    "stop_loss":179.74,
    "position_size":10.0,
    "adx_7":96.6874208695,
    "rsi_3":27.6464481406,
    "atr_10":8.2689926147,
    "avg_volume_50":11290237.8599999994,
    "avg_daily_value_50":1893023194.4249017239,
    "ma_100":158.0660998535
  },
  {
    "종목명":"ELF",
    "entry_price":118.57,
    "stop_loss":102.5,
    "position_size":10.0,
    "adx_7":80.7137502347,
    "rsi_3":19.3088882479,
    "atr_10":5.3589996338,
    "avg_volume_50":2858176.3599999999,
    "avg_daily_value_50":244216703.3234311044,
    "ma_100":77.7914001465
  },
  {
    "종목명":"TMDX",
    "entry_price":120.28,
    "stop_loss":102.18,
    "position_size":10.0,
    "adx_7":76.2623089164,
    "rsi_3":0.0,
    "atr_10":6.0332015991,
    "avg_volume_50":1098520.0,
    "avg_daily_value_50":118497454.7530517578,
    "ma_100":90.5091999817
  },
  {
    "종목명":"PODD",
    "entry_price":292.74,
    "stop_loss":270.41,
    "position_size":10.0,
    "adx_7":69.5651797122,
    "rsi_3":28.9940454424,
    "atr_10":7.4420043945,
    "avg_volume_50":851690.2,
    "avg_daily_value_50":248527286.6245361269,
    "ma_100":279.0709002686
  },
  {
    "종목명":"OKLO",
    "entry_price":60.16,
    "stop_loss":38.86,
    "position_size":5.65,
    "adx_7":67.1951380443,
    "rsi_3":34.2911742997,
    "atr_10":7.1009906769,
    "avg_volume_50":19121813.6000000015,
    "avg_daily_value_50":851517627.5453981161,
    "ma_100":35.960399971
  },
  {
    "종목명":"ETHT",
    "entry_price":37.98,
    "stop_loss":18.86,
    "position_size":3.97,
    "adx_7":65.5750211401,
    "rsi_3":42.5298754827,
    "atr_10":6.3709999561,
    "avg_volume_50":3873000.0,
    "avg_daily_value_50":26585835.8737506866,
    "ma_100":9.7240000391
  },
  {
    "종목명":"TT",
    "entry_price":407.26,
    "stop_loss":386.12,
    "position_size":10.0,
    "adx_7":61.5260927332,
    "rsi_3":43.6088845377,
    "atr_10":7.0469970703,
    "avg_volume_50":1426028.0,
    "avg_daily_value_50":557134930.5090942383,
    "ma_100":373.3606988525
  },
  {
    "종목명":"TEM",
    "entry_price":67.03,
    "stop_loss":52.15,
    "position_size":9.01,
    "adx_7":57.8015549537,
    "rsi_3":19.8895213928,
    "atr_10":4.9577991486,
    "avg_volume_50":13785058.0,
    "avg_daily_value_50":803392654.5385131836,
    "ma_100":57.2722499084
  },
  {
    "종목명":"CDNS",
    "entry_price":287.93,
    "stop_loss":268.03,
    "position_size":10.0,
    "adx_7":57.6948420685,
    "rsi_3":16.9455599466,
    "atr_10":6.6356414795,
    "avg_volume_50":2077034.9399999999,
    "avg_daily_value_50":604175338.8455145359,
    "ma_100":280.2956997681
  },
  {
    "종목명":"WING",
    "entry_price":339.81,
    "stop_loss":303.28,
    "position_size":10.0,
    "adx_7":55.681742318,
    "rsi_3":34.5454637168,
    "atr_10":12.1773010254,
    "avg_volume_50":822334.22,
    "avg_daily_value_50":239096016.3704199195,
    "ma_100":272.7799008179
  }
]