{"identity":{"schema_version":"1","namespace":"weinstein_stage2_symbol_analysis","market":"us","symbol":"ADAM","as_of":"2026-04-24","feature_version":"weinstein_stage2_symbol_analysis_v1","source":{"path":"E:\\side project\\invest-prototype-main\\data\\us\\ADAM.csv","mtime_ns":1777175656343470500,"size":44314},"extra_hash":"177458c6b378b7ffa3bd358b"},"row":{"symbol":"ADAM","market":"us","exchange":"NMS","benchmark_symbol":"SPY","mode":"BOOTSTRAP_MODE","market_state":"MARKET_STAGE2_FAVORABLE","group_state":"UNKNOWN","stock_stage":"STAGE_1","timing_state":"BASE","base_high":8.760000228881836,"base_low":6.159999847412109,"percent_to_stage2":10.188684767925448,"breakout_age_weeks":null,"weekly_close":7.949999809265137,"daily_close":7.949999809265137,"ma10w":7.763999938964844,"ma30w":7.555999978383382,"ma40w":7.426499974727631,"ma50d":7.833199987411499,"ma200d":7.375549991130828,"ma30w_slope_4w":0.00206832147938818,"ma40w_slope_4w":0.0034209177294697857,"rp":1.1135389223294854,"mrs":0.25301194674529626,"rs_proxy":0.13868117834782612,"rp_ma52_slope":0.0010838840218637125,"weekly_volume_ratio":1.0279476773380969,"weekly_volume_reference":"4w","overhead_reference":8.760000228881836,"resistance_confidence":"LOW","breadth150_market":52.991452991452995,"breadth150_group":75.0,"early_stage2_score":47.01,"confidence_tier":"MEDIUM","priority_label":"WATCH","rejection_reason":"base_not_close_enough_to_breakout","sector":"Real Estate","industry_group":"REIT - Mortgage","assumption_flags":["bootstrap_mode","missing_104w_resistance","missing_core_group"],"confidence_penalty_points":14,"base_duration_weeks":51,"base_quality_score":0.9473899030746114,"group_name":"REIT - Mortgage","group_truth_source":"local_proxy","retest_signal":false,"retest_volume_lighter":false,"breakout_level":null,"breakout_date":null,"breakout_type":null,"continuation_setup_pass":false,"continuation_quality_score":0.7898063041724617,"continuation_lifecycle_state":"EARLY","continuation_volume_dryup_ratio":1.0405458789728856,"breakout_structure_pass":false,"close_gt_ma10w":true,"close_gt_ma40w":true,"close_gt_ma50d":true,"close_gt_ma200d":true,"ma50d_gt_ma200d":true,"bar_end_date":"2026-04-24"}}